Metadata-Version: 2.2
Name: screen-watcher-ig
Version: 1.1.0
Summary: 화면 변경 감지 모니터링 프로그램
Home-page: https://github.com/rudclthe/screen-watcher-ig
Author: rudclthe
Author-email: your_email@example.com
Classifier: Programming Language :: Python :: 3
Classifier: Operating System :: MacOS
Requires-Python: >=3.6
Requires-Dist: numpy
Requires-Dist: opencv-python
Requires-Dist: pynput
Requires-Dist: pyobjc-framework-Quartz
Requires-Dist: pync
Dynamic: author
Dynamic: author-email
Dynamic: classifier
Dynamic: description
Dynamic: description-content-type
Dynamic: home-page
Dynamic: requires-dist
Dynamic: requires-python
Dynamic: summary
